[{
        "id": "tmec30",
        "name": "MEK-D",
        "about": "MEC",
        "contact": [{
            "name": "M. Sai kumar",
            "phone": "+919109191001"
        }, {
            "name": "",
            "phone": ""
        }]
    },
    {
        "id": "tmec31",
        "name": "Brain Buzz",
        "about": "MEC",
        "contact": [{
            "name": "D. Sai Varun Reddy",
            "phone": "+919109191001"
        }, {
            "name": "V.S.S. Rakesh",
            "phone": "+919109191001"
        }]
    },
    {
        "id": "tmec32",
        "name": "Stick Mechanism",
        "about": "MEC",
        "contact": [{
            "name": "G. Keerthi",
            "phone": "+919109191001"
        }, {
            "name": "P. Shankar",
            "phone": "+919109191001"
        }]
    },
    {
        "id": "tmec33",
        "name": "Entraptions",
        "about": "MEC",
        "contact": [{
            "name": "Sandeep",
            "phone": "+919109191001"
        }, {
            "name": "Koushik",
            "phone": "+919109191001"
        }]
    },
    {
        "id": "tmec34",
        "name": "Mech Hunt",
        "about": "MEC",
        "contact": [{
            "name": "K. Likith",
            "phone": "+919109191001"
        }, {
            "name": "Pranathi",
            "phone": "+919109191001"
        }]
    },
    {
        "id": "tmec35",
        "name": "MEK-Link",
        "about": "MEC",
        "contact": [{
            "name": "G. Keerthi",
            "phone": "+919109191001"
        }, {
            "name": "P. Shankar",
            "phone": "+919109191001"
        }]
    },
    {
        "id": "tmec36",
        "name": "Brain Fade",
        "about": "MEC",
        "contact": [{
            "name": "Venu Madhav",
            "phone": "+919109191001"
        }, {
            "name": "Sreenith",
            "phone": "+919109191001"
        }]
    },
    {
        "id": "tmec37",
        "name": "Project Expo",
        "about": "MEC",
        "contact": [{
            "name": "Raja Ratan M",
            "phone": "+919109191001"
        }, {
            "name": "",
            "phone": ""
        }]
    }
]